{
    "neoforge:conditions": [
        {
            "type": "neoforge:mod_loaded",
            "modid": "productivetrees"
        },
        {
            "type": "neoforge:mod_loaded",
            "modid": "would"
        }
    ],

    "type": "productivetrees:sawmill",
    "input": {
        "tag": "would:maple_logs"
    },
    "output": {
        "count": 6,
        "id": "would:maple_planks"
    },
    "secondary": {
        "count": 2,
        "id": "productivetrees:sawdust"
    },
    "tertiary": {}
}