{
    "neoforge:conditions": [
        {
            "type": "neoforge:mod_loaded",
            "modid": "integrateddynamics"
        },
        {
            "type": "neoforge:not",
            "value": {
                "type": "neoforge:tag_empty",
                "registry": "minecraft:item",
                "tag": "c:ores/neodymium"
            }
        },
        {
            "type": "neoforge:not",
            "value": {
                "type": "neoforge:tag_empty",
                "registry": "minecraft:item",
                "tag": "c:raw_materials/neodymium"
            }
        }
    ],
    "type": "integrateddynamics:squeezer",
    "input_item": {
        "tag": "c:ores/neodymium"
    },
    "output_items": [
        {
            "tag": {
                "tag": "c:raw_materials/neodymium",
                "count": 2
            }
        },
        {
            "tag": {
                "tag": "c:raw_materials/neodymium"
            },
            "chance": 0.75
        }
    ],
    "duration": 40
}