{
    "neoforge:conditions": [
        {
            "type": "neoforge:mod_loaded",
            "modid": "immersiveengineering"
        },
        {
            "type": "neoforge:mod_loaded",
            "modid": "natures_spirit"
        }
    ],

    "type": "immersiveengineering:sawmill",
    "energy": 800,
    "input": [
        {
            "item": "natures_spirit:stripped_willow_log"
        },
        {
            "item": "natures_spirit:stripped_willow_wood"
        }
    ],
    "result": {
        "basePredicate": {
            "item": "natures_spirit:willow_planks"
        },
        "count": 6
    },
    "secondaryOutputs": [
        {
            "tag": "c:dusts/wood"
        }
    ],
    "strippingSecondaries": []
}